ralph/__init__.py
ralph/__main__.py
ralph/cli.py
ralph/conf.py
ralph/exceptions.py
ralph/filters.py
ralph/logger.py
ralph/parsers.py
ralph/utils.py
ralph/api/__init__.py
ralph/api/auth.py
ralph/api/forwarding.py
ralph/api/models.py
ralph/api/routers/__init__.py
ralph/api/routers/health.py
ralph/api/routers/statements.py
ralph/backends/__init__.py
ralph/backends/mixins.py
ralph/backends/database/__init__.py
ralph/backends/database/base.py
ralph/backends/database/clickhouse.py
ralph/backends/database/es.py
ralph/backends/database/mongo.py
ralph/backends/http/__init__.py
ralph/backends/http/base.py
ralph/backends/http/lrs.py
ralph/backends/storage/__init__.py
ralph/backends/storage/base.py
ralph/backends/storage/fs.py
ralph/backends/storage/ldp.py
ralph/backends/storage/s3.py
ralph/backends/storage/swift.py
ralph/backends/stream/__init__.py
ralph/backends/stream/base.py
ralph/backends/stream/ws.py
ralph/models/__init__.py
ralph/models/converter.py
ralph/models/selector.py
ralph/models/validator.py
ralph/models/edx/__init__.py
ralph/models/edx/base.py
ralph/models/edx/browser.py
ralph/models/edx/server.py
ralph/models/edx/converters/__init__.py
ralph/models/edx/converters/xapi/__init__.py
ralph/models/edx/converters/xapi/base.py
ralph/models/edx/converters/xapi/navigational.py
ralph/models/edx/converters/xapi/server.py
ralph/models/edx/converters/xapi/video.py
ralph/models/edx/enrollment/__init__.py
ralph/models/edx/enrollment/statements.py
ralph/models/edx/enrollment/fields/__init__.py
ralph/models/edx/enrollment/fields/contexts.py
ralph/models/edx/enrollment/fields/events.py
ralph/models/edx/navigational/__init__.py
ralph/models/edx/navigational/statements.py
ralph/models/edx/navigational/fields/__init__.py
ralph/models/edx/navigational/fields/events.py
ralph/models/edx/problem_interaction/__init__.py
ralph/models/edx/problem_interaction/statements.py
ralph/models/edx/problem_interaction/fields/__init__.py
ralph/models/edx/problem_interaction/fields/events.py
thibaultlebrun_ralph_malph-3.6.0.dist-info/LICENSE.md
thibaultlebrun_ralph_malph-3.6.0.dist-info/METADATA
thibaultlebrun_ralph_malph-3.6.0.dist-info/WHEEL
thibaultlebrun_ralph_malph-3.6.0.dist-info/entry_points.txt
thibaultlebrun_ralph_malph-3.6.0.dist-info/top_level.txt
thibaultlebrun_ralph_malph-3.6.0.dist-info/zip-safe
thibaultlebrun_ralph_malph-3.6.0.dist-info/RECORD
