Metadata-Version: 2.1
Name: thibaultlebrun-ralph-malph
Version: 3.6.0
Summary: The ultimate toolbox for your learning analytics
Home-page: https://openfun.github.io/ralph/
Author: Open FUN (France Universite Numerique)
Author-email: fun.dev@fun-mooc.fr
License: MIT
Keywords: Open edX,Analytics,xAPI,LRS
Classifier: Development Status :: 5 - Production/Stable
Classifier: Intended Audience :: Developers
Classifier: License :: OSI Approved :: MIT License
Classifier: Natural Language :: English
Classifier: Programming Language :: Python :: 3
Classifier: Programming Language :: Python :: 3.7
Classifier: Programming Language :: Python :: 3.8
Classifier: Programming Language :: Python :: 3.9
Classifier: Programming Language :: Python :: 3.10
Classifier: Programming Language :: Python :: 3.11
Requires-Python: >=3.7
License-File: LICENSE.md
Requires-Dist: langcodes (>=3.2.0)
Requires-Dist: pydantic[dotenv,email] (>=1.10.0)
Requires-Dist: rfc3987 (>=1.3.0)
Provides-Extra: backend-clickhouse
Requires-Dist: clickhouse-connect[numpy,pandas] (<0.6) ; extra == 'backend-clickhouse'
Requires-Dist: python-dateutil (>=2.8.2) ; extra == 'backend-clickhouse'
Provides-Extra: backend-es
Requires-Dist: elasticsearch (>=8.0.0) ; extra == 'backend-es'
Provides-Extra: backend-ldp
Requires-Dist: ovh (>=1.0.0) ; extra == 'backend-ldp'
Requires-Dist: requests (>=2.0.0) ; extra == 'backend-ldp'
Provides-Extra: backend-lrs
Requires-Dist: httpx (==0.24.1) ; extra == 'backend-lrs'
Requires-Dist: more-itertools (==9.1.0) ; extra == 'backend-lrs'
Provides-Extra: backend-mongo
Requires-Dist: pymongo[srv] (>=4.0.0) ; extra == 'backend-mongo'
Requires-Dist: python-dateutil (>=2.8.2) ; extra == 'backend-mongo'
Provides-Extra: backend-s3
Requires-Dist: boto3 (>=1.24.70) ; extra == 'backend-s3'
Requires-Dist: botocore (>=1.27.71) ; extra == 'backend-s3'
Provides-Extra: backend-swift
Requires-Dist: python-keystoneclient (>=5.0.0) ; extra == 'backend-swift'
Requires-Dist: python-swiftclient (>=4.0.0) ; extra == 'backend-swift'
Provides-Extra: backend-ws
Requires-Dist: websockets (>=10.3) ; extra == 'backend-ws'
Provides-Extra: ci
Requires-Dist: twine (==4.0.2) ; extra == 'ci'
Provides-Extra: cli
Requires-Dist: bcrypt (>=4.0.0) ; extra == 'cli'
Requires-Dist: click (>=8.1.0) ; extra == 'cli'
Requires-Dist: click-option-group (>=0.5.0) ; extra == 'cli'
Requires-Dist: sentry-sdk[fastapi] (>=1.9.0) ; extra == 'cli'
Provides-Extra: dev
Requires-Dist: bandit (==1.7.5) ; extra == 'dev'
Requires-Dist: black (==23.3.0) ; extra == 'dev'
Requires-Dist: factory-boy (==3.2.1) ; extra == 'dev'
Requires-Dist: flake8 (==6.0.0) ; extra == 'dev'
Requires-Dist: hypothesis (==6.75.6) ; extra == 'dev'
Requires-Dist: isort (==5.12.0) ; extra == 'dev'
Requires-Dist: logging-gelf (==0.0.26) ; extra == 'dev'
Requires-Dist: mkdocs (==1.4.3) ; extra == 'dev'
Requires-Dist: mkdocs-click (==0.8.0) ; extra == 'dev'
Requires-Dist: mkdocs-material (==9.1.15) ; extra == 'dev'
Requires-Dist: mkdocstrings[python-legacy] (==0.22.0) ; extra == 'dev'
Requires-Dist: moto (==4.1.10) ; extra == 'dev'
Requires-Dist: pydocstyle (==6.3.0) ; extra == 'dev'
Requires-Dist: pyfakefs (==5.2.2) ; extra == 'dev'
Requires-Dist: pylint (==2.17.4) ; extra == 'dev'
Requires-Dist: pytest (==7.3.1) ; extra == 'dev'
Requires-Dist: pytest-asyncio (==0.21.0) ; extra == 'dev'
Requires-Dist: pytest-cov (==4.0.0) ; extra == 'dev'
Requires-Dist: pytest-httpx (==0.22.0) ; extra == 'dev'
Provides-Extra: lrs
Requires-Dist: bcrypt (==4.0.1) ; extra == 'lrs'
Requires-Dist: fastapi (==0.95.2) ; extra == 'lrs'
Requires-Dist: h11 (>=0.11.0) ; extra == 'lrs'
Requires-Dist: httpx (==0.24.1) ; extra == 'lrs'
Requires-Dist: sentry-sdk (==1.24.0) ; extra == 'lrs'
Requires-Dist: uvicorn[standard] (==0.22.0) ; extra == 'lrs'
